singular_report_builder/__init__.py
singular_report_builder/report_builder.py
singular_report_builder/views.py
singular_report_builder/management/__init__.py
singular_report_builder/management/commands/__init__.py
singular_report_builder/management/commands/create_report.py
singular_report_builder/static/img/singular_logo.png
singular_report_builder/static/js/report_builder.js
singular_report_builder/templates/pdf_template_base.html
singular_report_builder/templates/web_template_base.html
singular_report_builder/templatetags/__init__.py
singular_report_builder/templatetags/templatetags.py
singular_report_builder-0.0.17.dist-info/METADATA
singular_report_builder-0.0.17.dist-info/WHEEL
singular_report_builder-0.0.17.dist-info/top_level.txt
singular_report_builder-0.0.17.dist-info/RECORD
